[
    {
      "Date": "12 may 2023",
      "OrderId": "№ 3478741",
      "Pname": "Gmail.com PVA",
      "Price": "$13.00",
      "Status": "Completed"
    },
    {
        "Date": "12 may 2023",
        "OrderId": "№ 3478741",
        "Pname": "Gmail.com PVA",
        "Price": "$13.00",
        "Status": "Completed"
      },
      {
        "Date": "12 may 2023",
        "OrderId": "№ 3478741",
        "Pname": "Gmail.com PVA",
        "Price": "$13.00",
        "Status": "Completed"
      },
      {
        "Date": "12 may 2023",
        "OrderId": "№ 3478741",
        "Pname": "Gmail.com PVA",
        "Price": "$13.00",
        "Status": "Completed"
      },
      {
        "Date": "12 may 2023",
        "OrderId": "№ 3478741",
        "Pname": "Gmail.com PVA",
        "Price": "$13.00",
        "Status": "Completed"
      },
      {
        "Date": "12 may 2023",
        "OrderId": "№ 3478741",
        "Pname": "Gmail.com PVA",
        "Price": "$13.00",
        "Status": "Completed"
      },
      {
        "Date": "12 may 2023",
        "OrderId": "№ 3478741",
        "Pname": "Gmail.com PVA",
        "Price": "$13.00",
        "Status": "Completed"
      },
      {
        "Date": "12 may 2023",
        "OrderId": "№ 3478741",
        "Pname": "Gmail.com PVA",
        "Price": "$13.00",
        "Status": "Completed"
      },
      {
        "Date": "12 may 2023",
        "OrderId": "№ 3478741",
        "Pname": "Gmail.com PVA",
        "Price": "$13.00",
        "Status": "Completed"
      },
      {
        "Date": "12 may 2023",
        "OrderId": "№ 3478741",
        "Pname": "Gmail.com PVA",
        "Price": "$13.00",
        "Status": "Completed"
      }
]
  